mlb/__init__.py
mlb/color.py
mlb/core.py
mlb/exception.py
mlb/mail.py
mlb/ml.py
mlb_core-0.0.4.dist-info/LICENSE
mlb_core-0.0.4.dist-info/METADATA
mlb_core-0.0.4.dist-info/WHEEL
mlb_core-0.0.4.dist-info/top_level.txt
mlb_core-0.0.4.dist-info/RECORD
